[{"url": "https://commercialobserver.com/2026/05/stuart-saft-real-estate-law-2026/", "title_tokens": ["selling", "socks", "stuart", "want", "saft"], "summary_tokens": ["transactions", "more", "where", "field", "estate", "career", "student", "early", "college", "leading", "counsel", "highlights", "including", "attorney", "article", "proved", "solidifying", "legal", "authority", "serving", "well", "leasing", "real", "saft", "acquisitions", "range", "property", "development", "across", "pivotal", "closing", "stuart", "over", "lawyer", "broad", "hospitality", "profiles", "trajectory", "safts", "financing", "correct", "companies", "path", "experiences", "country", "notable", "encompassed", "instincts", "sales", "prominent", "seasoned", "moment", "conversions", "detailing", "general"]}, {"url": "https://commercialobserver.com/2026/05/trinity-investments-sculptor-jw-marriott-marco-island-beach-resort/", "title_tokens": ["sculptor", "floridas", "gulf", "trinity", "835m", "resort", "coast", "oceanfront"], "summary_tokens": ["marriott", "floridas", "million", "estate", "marco", "soughtafter", "originated", "morgan", "financed", "highly", "courses", "flows", "transaction", "event", "beachfront", "stable", "real", "cash", "fargo", "coast", "beach", "multiple", "sculptor", "golf", "championship", "restaurants", "chase", "significant", "asset", "space", "resort", "wells", "island", "luxury", "upside", "loan", "rooms", "hotel", "acquired", "gulf", "extensive", "trinity", "investments", "representing", "potential", "cmbs", "features"]}, {"url": "https://commercialobserver.com/2026/05/sea-fire-grill-relocation-216-east-49th-street/", "title_tokens": ["fire", "49th", "relocating", "east", "grill", "space", "street", "12ksf", "restaurant"], "summary_tokens": ["seafood", "location", "block", "spot", "benjamin", "clientele", "current", "ceilings", "grill", "room", "allowing", "midtown", "dining", "evolve", "shaban", "feature", "existing", "main", "brand", "just", "retaining", "sinanaj", "12000squarefoot", "fire", "24foot", "while", "groups", "east", "space", "street", "restaurant", "rooms", "49th", "relocating", "owned", "private"]}, {"url": "https://commercialobserver.com/2026/05/westbridge-realty-residential-washington-heights/", "title_tokens": ["residential", "building", "plans", "westbridge", "washington", "heights", "files", "realty", "99unit"], "summary_tokens": ["count", "building", "proposed", "more", "broadway", "suggests", "heights", "units", "realty", "group", "projects", "project", "exemptions", "aiming", "potentially", "under", "associated", "residential", "retail", "westbridge", "york", "4388", "buildings", "485x", "city", "department", "would", "parking", "program", "same", "99unit", "spaces", "requirements", "include", "16story", "while", "workers", "washington", "developer", "incentive", "higher", "construction", "which", "wage", "plans", "manhattan", "offers", "filed", "utilize", "legislation", "67048squarefoot", "avoiding", "groundfloor"]}, {"url": "https://commercialobserver.com/2026/05/intuit-turbotax-retail-lease-one-willoughby-square/", "title_tokens": ["intuit", "turbotax", "retail", "square", "25ksf", "signs", "willoughby", "lease"], "summary_tokens": ["location", "company", "longterm", "square", "realty", "highlights", "retail", "brooklyn", "jemb", "downtown", "2500", "financial", "services", "avrs", "transaction", "assets", "storefront", "venture", "capital", "occupy", "office", "35story", "intuit", "turbotax", "signed", "appeal", "feet", "space", "willoughby", "partners", "joint", "tower", "brooklyns", "which", "growth", "businesses", "owned", "desirable", "lease", "groundfloor"]}, {"url": "https://rebusinessonline.com/nrp-group-breaks-ground-on-297-unit-affordable-housing-project-in-denton-texas/", "title_tokens": ["housing", "denton", "297unit", "breaks", "texas", "affordable", "group", "project", "ground"], "summary_tokens": ["truist", "297unit", "million", "area", "texas", "early", "units", "nine", "ranch", "group", "project", "first", "housing", "fourbedroom", "year", "feature", "buildings", "earning", "threestory", "development", "offering", "occupancy", "denton", "provided", "households", "situated", "income", "percent", "commenced", "arbor", "loan", "construction", "22acre", "site", "median", "next", "affordable", "ready", "anticipated", "bank"]}, {"url": "https://rebusinessonline.com/newcrestimage-completes-renovation-of-296-room-hotel-in-dallas/", "title_tokens": ["hotel", "dallas", "renovation", "newcrestimage", "296room", "completes"], "summary_tokens": ["food", "management", "296room", "comprehensive", "upgrades", "concepts", "area", "completed", "kitchen", "park", "renovation", "newcrestimage", "october", "2024", "include", "property", "dallas", "hospitality", "significant", "raven", "mockingbird", "highland", "investment", "beverage", "hotel", "verse", "enhancements", "acquired", "introduction", "dallasbased", "firm"]}, {"url": "https://rebusinessonline.com/walmart-supercenter-opens-200000-sf-store-within-shawnee-trail-in-celina-texas/", "title_tokens": ["200000", "supercenter", "shawnee", "trail", "within", "texas", "walmart", "opens", "celina", "store"], "summary_tokens": ["additional", "developments", "anchor", "begin", "texas", "public", "project", "first", "dining", "including", "retail", "shawnee", "supercenter", "year", "mixeduse", "collaboration", "trademark", "broader", "corp", "entertainment", "marks", "celina", "spaces", "glendenning", "development", "opened", "economic", "within", "1887", "significant", "walmart", "phase", "construction", "which", "150acre", "trail", "200000squarefoot", "slated", "next", "between", "opening"]}, {"url": "https://rebusinessonline.com/oxford-partners-arranges-11057-sf-industrial-lease-in-northwest-houston/", "title_tokens": ["11057", "industrial", "partners", "northwest", "oxford", "lease", "arranges", "houston"], "summary_tokens": ["landlord", "11057squarefoot", "while", "medical", "industrial", "provider", "westland", "tenant", "supplies", "represented", "realty", "partners", "stream", "northwest", "oxford", "lease", "houston", "arranged"]}, {"url": "https://rebusinessonline.com/jll-arranges-109-5m-loan-for-refinancing-of-apartment-building-in-edgewater-new-jersey/", "title_tokens": ["building", "jersey", "apartment", "refinancing", "1095m", "edgewater", "arranges", "loan"], "summary_tokens": ["building", "million", "estate", "edgewater", "arranged", "amenities", "variety", "capital", "pccp", "real", "sponsors", "property", "provided", "floatingrate", "skylight", "jersey", "underwent", "226unit", "apartment", "renovations", "sizes", "threeyear", "partners", "loan", "1095", "riello", "offers", "refinancing", "unit", "recently", "bridge"]}, {"url": "https://rejournals.com/st-louis-based-wiegmann-associates-adds-project-manager-project-engineers/?utm_source=rss&utm_medium=rss&utm_campaign=st-louis-based-wiegmann-associates-adds-project-manager-project-engineers", "title_tokens": ["project", "wiegmann", "associates", "adds", "louisbased", "engineers", "manager"], "summary_tokens": ["johnson", "calculations", "aaron", "load", "selection", "engineering", "projects", "project", "louisbased", "budget", "including", "quality", "commercial", "subcontractors", "schedule", "system", "designing", "equipment", "orders", "safety", "focus", "jared", "boettcher", "energyefficient", "wiegmann", "provider", "appointing", "edwards", "systems", "labor", "hvac", "oversee", "change", "modeling", "mechanical", "industrial", "associates", "team", "managing", "rfis", "engineers", "manager", "expanded"]}, {"url": "https://rejournals.com/commercial-real-estate-hall-of-fame-reed-christianson/?utm_source=rss&utm_medium=rss&utm_campaign=commercial-real-estate-hall-of-fame-reed-christianson", "title_tokens": ["commercial", "fame", "estate", "hall", "real", "christianson", "reed"], "summary_tokens": ["minneapolis", "btnsm", "focused", "estate", "sincepa", "servicesminneapolis", "real", "moreap", "understrapreadmorelink", "christianson", "office", "christiansonprincipaltranswestern", "reed", "targetblanklearn", "principal", "transwestern", "hrefhttpsrejournalscomfeed", "classbtn", "market", "btnoutlineprimary", "services"]}, {"url": "https://rejournals.com/lee-associates-brokers-40873-square-foot-industrial-lease-in-elgin/?utm_source=rss&utm_medium=rss&utm_campaign=lee-associates-brokers-40873-square-foot-industrial-lease-in-elgin", "title_tokens": ["40873squarefoot", "brokers", "industrial", "associates", "elgin", "lease"], "summary_tokens": ["illinois", "service", "logistics", "center", "near", "represented", "properties", "tollway", "visibility", "brokered", "cushman", "tenant", "property", "landlord", "strategically", "while", "major", "business", "provider", "elgin", "wakefield", "street", "high", "located", "40873squarefoot", "specialty", "offers", "industrial", "river", "associates", "unit", "lease", "pharmaceutical"]}, {"url": "https://rejournals.com/rosemonts-lee-associates-adds-senior-associate/?utm_source=rss&utm_medium=rss&utm_campaign=rosemonts-lee-associates-adds-senior-associate", "title_tokens": ["rosemonts", "associates", "associate", "senior", "adds"], "summary_tokens": ["worked", "management", "kwill", "estate", "previously", "concentrate", "area", "marco", "having", "hiring", "corridor", "broader", "real", "office", "experience", "focus", "kinzie", "chicagoland", "side", "role", "advisory", "asset", "rosemont", "market", "brings", "industrial", "stockyards", "associates", "team", "associate", "senior", "chicago", "particularly", "west", "federow", "expanded"]}, {"url": "https://therealdeal.com/national/2026/05/04/fha-safety-net-shrinks-setting-up-foreclosure-bump/", "title_tokens": ["shrinks", "foreclosures", "safety", "jump"], "summary_tokens": ["weaker", "once", "prices", "approximately", "absorbing", "leading", "missed", "administrations", "allowed", "defer", "restrictions", "potentially", "impact", "vary", "housing", "make", "claim", "every", "250000", "half", "existing", "tighter", "federal", "program", "months", "partial", "analysts", "driven", "ontime", "requirements", "homeowners", "foreclosure", "these", "limiting", "seriously", "home", "consecutive", "while", "price", "reductions", "three", "over", "payments", "rules", "march", "stronger", "filings", "delinquent", "yearoveryear", "requiring", "distressed", "access", "which", "market", "predict", "next", "markets", "borrowers", "sales", "meet", "stricter", "years", "equity", "increased"]}, {"url": "https://therealdeal.com/national/2026/05/04/listen-chetrit-empire-on-the-brink/", "title_tokens": ["chetrit", "listen", "brink", "empire"], "summary_tokens": ["difficulties", "allegations", "building", "secured", "alleged", "discusses", "florida", "estate", "family", "properties", "lawsuits", "group", "neglect", "seventh", "recent", "article", "extensions", "avenue", "challenges", "issues", "towers", "security", "despite", "york", "real", "tenant", "stabilize", "their", "office", "include", "these", "indicating", "deposits", "meyer", "indigo", "chetrit", "series", "significant", "efforts", "rentstabilized", "accusations", "empire", "mismanagement", "harassment", "loan", "hotel", "highlighting", "faced", "workouts", "williamsburg", "transferring", "joseph"]}, {"url": "https://therealdeal.com/national/2026/05/04/ai-investor-coatue-launches-data-center-land-venture/", "title_tokens": ["launches", "center", "venture", "data", "investor", "land"], "summary_tokens": ["management", "focused", "dollars", "center", "complex", "projects", "land", "computing", "begun", "acquiring", "430megawatt", "fluidstack", "invest", "venture", "data", "investor", "firms", "explore", "lebanon", "indiana", "formed", "development", "launched", "frontier", "provider", "prepared", "already", "billions", "joint", "tens", "next", "coatue", "also", "firm", "potential", "services"]}, {"url": "https://therealdeal.com/magazine/may-2026/", "title_tokens": ["2026"], "summary_tokens": ["company", "deal", "estate", "information", "only", "preventing", "original", "article", "text", "story", "transaction", "extraction", "real", "content", "does", "includes", "provided", "contain", "analysis", "link", "details", "market", "full", "reprint", "commentary"]}, {"url": "https://therealdeal.com/new-york/2026/05/04/eviction-bill-draws-concern-hochul-tweaks-pied-a-terre-tax/", "title_tokens": ["policypro", "nyaa", "draws", "eviction", "hochul", "warning", "revises", "bill", "piedterre"], "summary_tokens": ["proposed", "million", "nonprofit", "providers", "including", "hands", "values", "data", "tenant", "unreliable", "revising", "assessed", "repairs", "evictions", "apartment", "compliance", "strong", "using", "hochuls", "rentescrow", "based", "process", "sales", "oversight", "they", "building", "moving", "scope", "initiating", "opposition", "instead", "owners", "office", "rentregulated", "certification", "over", "alternative", "could", "which", "accessing", "kathy", "work", "units", "properties", "valued", "prevent", "completed", "lengthy", "piedterre", "proposes", "york", "mechanism", "makes", "would", "destabilize", "city", "their", "yorks", "broad", "drawing", "argues", "landlords", "practical", "finances", "also", "difficulties", "away", "court", "housing", "nyaa", "guaranteed", "model", "governor", "bills", "while", "considering", "active", "comparable", "violations", "separately", "access", "highlight", "impossible", "clean", "owner", "association", "nearly"]}, {"url": "https://therealdeal.com/new-york/2026/05/04/court-revives-eli-karps-madison-realty-capital-claim/", "title_tokens": ["claim", "karps", "against", "capital", "loantoown", "realty", "court", "madison", "revives"], "summary_tokens": ["lawsuit", "building", "ultimately", "million", "reinstated", "complex", "only", "loantoown", "realty", "pursue", "court", "promises", "allowing", "madison", "project", "stalled", "completed", "brooklyn", "alleges", "avenue", "default", "rental", "pushing", "control", "capital", "scheme", "2021", "1580", "related", "property", "development", "developer", "karps", "apartment", "against", "credit", "hello", "deliberately", "nostrand", "karp", "after", "appellate", "seize", "false", "plans", "acquired", "made", "fund", "claims"]}, {"url": "https://therealdeal.com/new-york/2026/05/04/nycs-top-retail-leases-april-2026/", "title_tokens": ["retail", "inks", "nycs", "biggest", "deal", "life", "time", "april"], "summary_tokens": ["central", "leases", "15300squarefoot", "retailer", "life", "71000", "square", "demand", "categories", "highlights", "retail", "york", "upper", "city", "another", "other", "brand", "22000squarefoot", "outerborough", "development", "across", "side", "signed", "16000squarefoot", "continued", "district", "time", "significant", "lease", "feet", "plaza", "grand", "relocation", "restaurant", "clothing", "concept", "activity", "largest", "manhattan", "west", "april", "various", "submarkets", "williamsburg", "included", "taking"]}, {"url": "https://therealdeal.com/new-york/2026/05/04/bawabeh-holdings-seeks-to-rezone-east-flatbush-site/", "title_tokens": ["development", "flatbush", "site", "rezone", "east", "bawabeh", "seeks"], "summary_tokens": ["proposed", "planned", "bawabeh", "units", "project", "seeking", "brooklyn", "housing", "residential", "completion", "deliver", "currently", "buildings", "ninebuilding", "zoned", "aims", "phases", "development", "holdings", "rezoning", "2035", "east", "designated", "approval", "necessitating", "15story", "millionsquarefoot", "flatbush", "site", "industrial", "affordable", "anticipated"]}, {"url": "https://therealdeal.com/new-york/2026/05/04/proposed-ues-mansion-tops-manhattans-luxury-contracts/", "title_tokens": ["proposed", "manhattans", "contracts", "mansion", "luxury", "tops"], "summary_tokens": ["topped", "proposed", "combining", "million", "homes", "12500squarefoot", "deal", "borough", "last", "demand", "properties", "mansion", "highlights", "residential", "manhattans", "residence", "even", "existing", "eightbedroom", "upper", "transaction", "asking", "week", "price", "formed", "property", "includes", "slightly", "side", "contract", "continued", "east", "cityapproved", "highend", "dipped", "luxury", "number", "market", "which", "fivestory", "plans", "overall", "contracts", "highest"]}, {"url": "https://therealdeal.com/miami/2026/05/04/south-florida-top-real-estate-deals-may-4-2026/", "title_tokens": ["boca", "floridas", "cortland", "sells", "240m", "south", "deals", "raton", "apartments"], "summary_tokens": ["million", "deal", "florida", "complex", "approximately", "uptown", "reserve", "643000squarefoot", "boca", "commercial", "cortland", "526000", "transaction", "residences", "marks", "property", "apartment", "situated", "significant", "partners", "market", "acquired", "456unit", "south", "acres", "raton", "equates", "sale"]}, {"url": "https://therealdeal.com/miami/2026/05/04/adam-neumanns-flow-buys-out-pmg-in-society-wynwood/", "title_tokens": ["stake", "wynwood", "buys", "adam", "apartments", "flow", "neumanns"], "summary_tokens": ["allocated", "additional", "rebrand", "million", "adam", "318unit", "society", "miami", "wynwood", "renovate", "stake", "expenditures", "multifamily", "capital", "acquisition", "property", "rebranding", "efforts", "asset", "investment", "greybrook", "initial", "coown", "involved", "plans", "acquired", "flow", "neumanns"]}, {"url": "https://therealdeal.com/miami/2026/05/04/al-capones-ex-miami-beach-property-in-contract/", "title_tokens": ["contract", "miami", "former", "capones", "beach", "under", "property"], "summary_tokens": ["million", "named", "palm", "last", "properties", "miami", "capone", "under", "trend", "totaling", "dollar", "part", "demolished", "transaction", "broader", "county", "asking", "2021", "week", "volume", "beach", "price", "property", "waterfront", "home", "contract", "2023", "1463", "island", "luxury", "after", "formerly", "acquired", "contracts", "owned", "seller", "miamidade", "going"]}, {"url": "https://therealdeal.com/miami/2026/05/04/perez-familys-related-sells-apartment-tower-to-lefrak/", "title_tokens": ["fort", "lefrak", "180m", "portfolio", "riverfront", "beefs", "lauderdale", "tower"], "summary_tokens": ["floridas", "ongoing", "million", "developments", "deal", "oversupply", "harbour", "apartments", "properties", "group", "lauderdale", "completed", "trend", "financed", "highlights", "mutual", "multifamily", "36story", "downtown", "lefrak", "part", "larger", "transaction", "2024", "other", "related", "property", "region", "continued", "organization", "rabina", "significant", "investment", "337unit", "loan", "market", "which", "involved", "acquired", "fort", "activity", "south", "river", "also", "northwestern", "despite"]}, {"url": "https://therealdeal.com/chicago/2026/05/04/menashe-buying-discounted-chicago-loop-office-tower/", "title_tokens": ["menashe", "again", "lasalle", "street", "strikes", "discount", "massive", "tower"], "summary_tokens": ["central", "acquire", "estimated", "menashe", "million", "loop", "future", "caisse", "properties", "googles", "under", "1985", "lasalle", "38story", "less", "downtown", "assets", "pension", "buildings", "canadian", "firms", "marks", "office", "acquisition", "strategy", "property", "betting", "drive", "rebound", "contract", "north", "headquarters", "three", "substantial", "significant", "street", "2016", "purchasing", "discount", "tower", "distressed", "than", "which", "market", "acquired", "third", "fund", "continuing", "loss", "chicago", "seller", "years", "proximity", "taking"]}, {"url": "https://therealdeal.com/chicago/2026/05/04/friedman-names-new-chicago-lead/", "title_tokens": ["market", "names", "lead", "estate", "real", "chicago", "movers", "friedman"], "summary_tokens": ["management", "citys", "local", "estate", "kramer", "deal", "properties", "competitive", "stratis", "knowledge", "herea", "offices", "friedman", "including", "columbus", "article", "commercial", "lead", "multifamily", "inland", "roles", "michigan", "release160", "announced", "estates", "real", "release", "firms", "other", "draper", "growing", "star", "experience", "according", "property", "operations", "leadership", "late", "chicagos", "market160", "over", "role", "read", "joins", "originally", "hills", "snagging", "appeared", "companies", "market", "each", "hrefhttpstherealdealcomchicago20260504friedmannamesnewchicagoleadutmsourcefeed038utmmediumfeedclick", "farmington", "tasked", "press", "chicago", "april", "wins", "recently", "employees", "years", "8230pthis", "most", "full", "taking", "storyp"]}, {"url": "https://therealdeal.com/texas/2026/05/04/ksl-capital-partners-acquires-invited-clubs/", "title_tokens": ["clubs", "invited", "acquires", "capital", "irvingbased", "partners"], "summary_tokens": ["management", "company", "national", "operates", "approximately", "sector", "leisure", "highlights", "including", "operator", "clubs", "invited", "transaction", "capital", "city", "interest", "marks", "golf", "private", "across", "membership", "continued", "reacquired", "over", "global", "time", "partners", "second", "which", "country", "debt", "owned", "equity", "billion", "apollo"]}, {"url": "https://therealdeal.com/texas/2026/05/04/judge-delays-new-texas-hemp-rules/", "title_tokens": ["stricter", "retailers", "hemp", "delays", "state", "texas", "judge", "their", "rules", "enforcement", "hold", "breath"], "summary_tokens": ["proposed", "least", "1500", "estimated", "uncertainty", "whom", "seen", "distribution", "order", "texas", "regulations", "extending", "products", "states", "many", "transport", "reliant", "legal", "total", "increases", "pause", "july", "threat", "prolongs", "occupy", "warehousing", "judge", "growing", "include", "operations", "across", "retailers", "groups", "temporarily", "late", "consumable", "until", "significant", "impacts", "rapidly", "rules", "space", "licensing", "centers", "market", "hemp", "which", "steep", "restraining", "shopping", "industrial", "state", "industry", "also", "interstate", "blocked", "shipping"]}, {"url": "https://therealdeal.com/texas/2026/05/04/fermi-ex-ceo-toby-neugebauer-sues-company-after-firing/", "title_tokens": ["lawsuit", "texas", "sacked", "hits", "wrongful", "reit", "termination", "fermi"], "summary_tokens": ["lawsuit", "criticism", "neugebauer", "company", "center", "seen", "board", "wrongful", "departure", "reit", "texasbased", "project", "legal", "toby", "action", "data", "stock", "fired", "former", "price", "development", "alleging", "about", "against", "challenging", "misled", "comes", "matador", "investors", "plummet", "amidst", "which", "ambitious", "unleased", "period", "without", "filed", "immediate", "faced", "cause", "sale", "termination", "fermi", "advocating"]}, {"url": "https://therealdeal.com/texas/2026/05/04/texas-biggest-loans-headed-to-foreclosure-auctions-in-may/", "title_tokens": ["past", "multifamily", "distress", "auctions", "foreclosures", "texas", "surge", "fueled"], "summary_tokens": ["austin", "building", "distress", "primarily", "million", "estate", "foreclosures", "complex", "texas", "crossed", "units", "sector", "properties", "first", "counties", "totaling", "tarrant", "commercial", "past", "multifamily", "facing", "threshold", "majority", "2025", "antonio", "portfolio", "real", "auction", "office", "surged", "driven", "marking", "covering", "indicates", "include", "across", "major", "foreclosure", "dallas", "additionally", "apartment", "time", "352unit", "fourproperty", "analysis", "like", "forming", "mortgage", "loan", "complexes", "since", "fort", "worth", "slated", "notable", "1530", "metros", "248unit", "billion", "houston"]}, {"url": "https://therealdeal.com/magazine/may-2026/cattle-call/", "title_tokens": ["fort", "blood", "expansion", "succession", "majestic", "stockyards", "sweat", "realty", "worths", "holds", "billiondollar"], "summary_tokens": ["more", "million", "litigation", "company", "area", "promised", "vice", "sweat", "realty", "pursue", "stalled", "projects", "gradual", "commented", "including", "executive", "stake", "alleges", "legal", "demanding", "equity", "delightful", "fired", "former", "loans", "repayment", "shifting", "development", "while", "leadership", "president", "launched", "cavileer", "amid", "district", "within", "historic", "denying", "transition", "thereby", "dispute", "phase", "individual", "initial", "second", "revitalization", "approach", "familyowned", "foreclosed", "fort", "worth", "expansion", "craig", "ownership", "reportedly", "immediate", "majestic", "stockyards", "firm", "between", "spearheaded", "billion"]}, {"url": "https://therealdeal.com/san-francisco/2026/05/04/pacific-heights-mansion-fetches-nearly-30-million/", "title_tokens": ["market", "heats", "sells", "spring", "heights", "mansion"], "summary_tokens": ["reflects", "linked", "million", "entity", "heights", "inventory", "limited", "hennessey", "mansion", "financial", "tech", "identity", "transaction", "capital", "city", "undisclosed", "purchased", "driven", "rajiv", "though", "2010", "property", "remains", "colonial", "president", "2023", "ghatalia", "francisco", "buyer", "originally", "luxury", "specific", "wealth", "pacific", "market", "tied", "listed", "heating", "seller", "georgian", "firm", "sold", "franciscos", "services"]}, {"url": "https://therealdeal.com/san-francisco/2026/05/04/meta-abandons-mixed-use-menlo-park-megadevelopment/", "title_tokens": ["park", "menlo", "jump", "profit", "brakes", "amid", "pumps", "mixeduse", "megaproject", "meta"], "summary_tokens": ["received", "million", "estate", "square", "units", "firstquarter", "project", "reducing", "aligns", "residential", "park", "retail", "amenities", "1730", "workforce", "tech", "footprint", "mixeduse", "broader", "city", "evolving", "real", "village", "profits", "office", "platforms", "requirements", "include", "strategy", "development", "2022", "designed", "designated", "approval", "significant", "willow", "challenging", "feet", "space", "meta", "indefinitely", "market", "menlo", "citing", "which", "ambitious", "decision", "giants", "shelved", "affordable", "reporting", "various", "increase", "nearly", "despite"]}, {"url": "https://therealdeal.com/san-francisco/2026/05/04/bay-area-condo-prices-fall-except-in-tony-san-francisco-areas/", "title_tokens": ["wider", "neighborhoods", "tony", "value", "slump", "area", "prices", "condo", "buck"], "summary_tokens": ["they", "signal", "sharper", "shift", "nearly", "area", "approximately", "demand", "units", "sector", "rise", "properties", "rents", "supply", "competition", "rental", "increasing", "segments", "acquiring", "values", "city", "condo", "marks", "driven", "topping", "while", "momentum", "within", "reversal", "wave", "percent", "five", "modest", "like", "areas", "marina", "constrained", "street", "valley", "after", "wealth", "investors", "creating", "codes", "market", "located", "change", "available", "higherend", "experiencing", "access", "condominium", "notable", "declines", "eight", "typical", "artificial", "direct", "gains", "intelligence", "also", "particularly", "conversions", "years", "district", "franciscos"]}, {"url": "https://www.connectcre.com/stories/trepps-lonnie-hendry-emphasizes-discipline-patience-and-data/", "title_tokens": ["trepps", "hendry", "emphasizes", "patience", "data", "lonnie", "discipline"], "summary_tokens": ["realistic", "current", "throughout", "estate", "decisionmaking", "beyond", "leading", "types", "lonnie", "leverage", "discipline", "resetting", "notes", "struggle", "highlights", "rents", "commercial", "hendry", "emphasizing", "even", "conservative", "patience", "risk", "bifurcation", "opportunities", "need", "assets", "concern", "transaction", "capital", "real", "volume", "classa", "loans", "points", "healthy", "property", "across", "major", "nongateway", "performance", "product", "previous", "2026", "significant", "levels", "asset", "strong", "maturity", "investors", "market", "trepp", "outperforming", "activity", "trends", "emerging", "refinance", "markets", "datadriven", "operators", "refinancing", "anticipates", "also", "confidence", "lenders", "officer", "chief", "increase", "particularly", "underwrite", "despite", "unresolved"]}, {"url": "https://www.connectcre.com/stories/kennedy-wilsons-mac-bernie-sees-deal-market-become-increasingly-competitive/", "title_tokens": ["market", "become", "wilsons", "deal", "sees", "competitive", "bernie", "kennedy", "increasingly"], "summary_tokens": ["consistent", "more", "million", "typically", "deal", "shift", "early", "6065", "insurance", "competitive", "group", "allowing", "notes", "agencylongerterm", "often", "banks", "maintains", "multifamily", "when", "conservative", "prevalent", "2025", "reentry", "other", "bernie", "compared", "evenly", "driven", "nonrecourse", "wilson", "loantocost", "towards", "property", "observes", "underwriting", "specializes", "wilsons", "alternative", "years", "investment", "increasingly", "financing", "approach", "companies", "market", "construction", "since", "lending", "debt", "subordinate", "refinancing", "director", "sales", "managing", "lenders", "particularly", "takeouts", "kennedy", "senior", "between", "bridge", "split"]}, {"url": "https://www.connectcre.com/stories/cushman-wakefield-arranges-refi-for-south-bronx-class-a-multifamily/", "title_tokens": ["multifamily", "cushman", "south", "refi", "bronx", "wakefield", "class", "arranges"], "summary_tokens": ["reports", "transactions", "editor", "connect", "where", "current", "estate", "career", "businesstobusiness", "paul", "manages", "highlights", "article", "commercial", "serving", "daily", "prior", "real", "develops", "content", "experience", "operations", "includes", "publishing", "bubny", "biography", "role", "professional", "journalism", "globestcom", "longerform", "forum", "market", "extensive", "trends", "director", "managing", "senior", "detailing"]}, {"url": "https://www.connectcre.com/stories/greenstone-partners-brokers-sale-of-skokie-retail-center/", "title_tokens": ["retail", "greenstone", "brokers", "center", "sale", "partners", "skokie"], "summary_tokens": ["crossing", "illinois", "optimization", "opportunity", "million", "leaseup", "center", "brokered", "supplyconstrained", "highlights", "retail", "welllocated", "assets", "transaction", "interest", "occupied", "property", "offering", "gross", "continued", "rent", "time", "buyer", "3875", "partners", "strong", "point", "through", "skokie", "greenstone", "markets", "19000squarefoot", "sale", "suburban", "valueadd"]}, {"url": "https://www.connectcre.com/stories/owner-user-acquires-corona-drive-thru-restaurant/", "title_tokens": ["drivethru", "acquires", "owneruser", "corona", "restaurant"], "summary_tokens": ["location", "building", "propertys", "million", "offered", "opportunity", "flexible", "lower", "predictable", "future", "demand", "properties", "corona", "attractive", "open", "welllocated", "options", "inland", "monetization", "transaction", "investor", "carry", "vacant", "requirement", "provided", "2230squarefoot", "drivethru", "income", "troys", "buyer", "strong", "initial", "stream", "empire", "restaurant", "financing", "reflecting", "which", "burgers", "plans", "highvisibility", "acquired", "made", "seller", "equity", "structured", "private"]}, {"url": "https://www.bisnow.com/charlotte/news/office/smbc-officially-commits-to-charlotte-signing-lease-for-200k-sf-at-new-hq-134409", "title_tokens": ["200k", "charlotte", "scoops", "smbc"], "summary_tokens": ["jobs", "mitsui", "million", "company", "2000", "square", "college", "demand", "charlottes", "class", "locations", "200000", "amenities", "financial", "invest", "transaction", "expected", "city", "grant", "corp", "leasing", "buildings", "single", "convenient", "office", "toptier", "development", "north", "signed", "headquarters", "over", "tokyobased", "significant", "feet", "space", "investment", "strong", "second", "supported", "banking", "establishing", "market", "reflecting", "plans", "activity", "carolina", "sumitomo", "next", "largest", "sublease", "create", "smbc", "years", "charlotte", "services"]}, {"url": "https://www.bisnow.com/atlanta/news/mixed-use/repeating-the-braves-battery-success-with-other-teams-unrealistic-134406", "title_tokens": ["experts", "easy", "story", "looks", "want", "atlanta", "developers", "success", "copy", "battery"], "summary_tokens": ["truist", "teams", "developments", "caution", "anchored", "campus", "last", "replicating", "demand", "programming", "projects", "project", "planning", "record", "prompting", "park", "retail", "year", "collegiate", "programs", "mixeduse", "governmental", "careful", "support", "other", "attributed", "explore", "experience", "generated", "focusing", "generate", "similar", "offerings", "significant", "challenging", "revenue", "rather", "experts", "restaurant", "battery", "requiring", "sports", "approach", "market", "than", "enhancing", "builditandtheywillcome", "some", "understanding", "however", "stadium", "strategic", "looking", "universities", "also", "atlanta", "success", "deep"]}, {"url": "https://www.bisnow.com/national/news/multifamily/feds-look-for-deal-with-1500-landlords-suing-over-pandemic-era-eviction-ban-134403", "title_tokens": ["1500", "look", "suing", "landlords", "deal", "over", "eviction", "feds", "pandemicera"], "summary_tokens": ["opening", "lawsuit", "1500", "lost", "allowed", "proceed", "potentially", "thousands", "seeking", "claim", "2025", "federal", "their", "settlement", "classaction", "door", "development", "damages", "rights", "constitutionality", "similar", "over", "eviction", "rent", "against", "denying", "appeal", "challenging", "successful", "government", "pandemicera", "entered", "moratorium", "them", "violated", "follows", "compensation", "brought", "negotiations", "landlords", "fifth", "claims", "amendment", "june", "billion"]}, {"url": "https://www.bisnow.com/san-francisco/news/office/olema-pharmaceuticals-leases-new-headquarters-south-san-francisco-134419", "title_tokens": ["olema", "leases", "south", "francisco", "pharmaceuticals"], "summary_tokens": ["undertaking", "additional", "future", "pharmaceuticals", "realty", "kilroy", "completed", "options", "existing", "expected", "occupy", "tenant", "midseptember", "office", "spaces", "biotech", "includes", "oyster", "headquarters", "38100", "improvements", "francisco", "space", "25000", "point", "initially", "leased", "olema", "sevenyear", "13100", "corporate", "extension", "expansion", "relocating", "south", "firm", "lease"]}, {"url": "https://www.bisnow.com/national/news/data-center-capital-markets/blackstone-digital-infrastructure-trust-ipo-134402", "title_tokens": ["175b", "center", "blackstone", "data", "reit", "targets"], "summary_tokens": ["capitalize", "constructed", "focused", "raise", "million", "center", "entity", "valued", "public", "declined", "reit", "investmentgrade", "planning", "target", "bxdc", "acquiring", "existing", "assets", "blackstone", "data", "surges", "interest", "affiliated", "aims", "newly", "move", "occupied", "growing", "indicating", "offering", "hyperscalers", "returns", "development", "positioning", "stabilized", "higher", "comes", "initial", "shares", "purchasing", "trust", "centers", "market", "each", "infrastructure", "issuing", "anticipates", "digital", "sales", "firm", "between", "billion"]}]